hid_data_transfer_lib/__init__.py
hid_data_transfer_lib/conf/__init__.py
hid_data_transfer_lib/conf/hid_dt.cfg
hid_data_transfer_lib/conf/hid_dt_configuration.py
hid_data_transfer_lib/conf/hid_dt_local.cfg
hid_data_transfer_lib/conf/hid_dt_psnc.cfg
hid_data_transfer_lib/exceptions/__init__.py
hid_data_transfer_lib/exceptions/hid_dt_exceptions.py
hid_data_transfer_lib/hid_dt_lib.py
hid_data_transfer_lib/keycloak/__init__.py
hid_data_transfer_lib/keycloak/keycloak_rest.py
hid_data_transfer_lib/nifi/__init__.py
hid_data_transfer_lib/nifi/nifi_client.py
hid_data_transfer_lib/nifi/nifi_rest.py
hid_data_transfer_lib/py.typed
hid_data_transfer_lib/util/__init__.py
hid_data_transfer_lib/util/util.py
hid_data_transfer_lib-0.3.9.dist-info/METADATA
hid_data_transfer_lib-0.3.9.dist-info/WHEEL
hid_data_transfer_lib-0.3.9.dist-info/RECORD
