Metadata-Version: 2.3
Name: hid_data_transfer_lib
Version: 0.3.9
Summary: HiDALGO Data Transfer library provides methods to transfer data between different data providers and consumers using NIFI pipelines
License: APL-2.0
Author: Jesús Gorroñogoitia
Author-email: jesus.gorronogoitia@eviden.com
Requires-Python: >=3.11
Classifier: License :: Other/Proprietary License
Classifier: Programming Language :: Python :: 3
Classifier: Programming Language :: Python :: 3.11
Classifier: Programming Language :: Python :: 3.12
Classifier: Programming Language :: Python :: 3.13
Requires-Dist: paramiko (>=3.3.1)
Requires-Dist: requests (>=2.31.0)
Requires-Dist: setuptools (>=79.0.0,<80.0.0)
